wifi/__init__.py
wifi/__main__.py
display_wifi-1.0.0.dist-info/LICENSE
display_wifi-1.0.0.dist-info/METADATA
display_wifi-1.0.0.dist-info/WHEEL
display_wifi-1.0.0.dist-info/entry_points.txt
display_wifi-1.0.0.dist-info/top_level.txt
display_wifi-1.0.0.dist-info/RECORD
