Metadata-Version: 2.1
Name: display-wifi
Version: 1.0.0
Summary: wifi only has one command but two usages.
Home-page: UNKNOWN
Author: Anthony Maxwell
Author-email: amaxwell4013@gmail.com
License: MIT
Platform: UNKNOWN
Classifier: License :: OSI Approved :: MIT License
Classifier: Programming Language :: Python :: 3.6
Classifier: Programming Language :: Python :: 3.7
Classifier: Programming Language :: Python :: 3.8
